url_to_image/__init__.py
url_to_image-1.0.1.dist-info/LICENSE
url_to_image-1.0.1.dist-info/METADATA
url_to_image-1.0.1.dist-info/WHEEL
url_to_image-1.0.1.dist-info/top_level.txt
url_to_image-1.0.1.dist-info/RECORD
