Metadata-Version: 2.1
Name: url-to-image
Version: 1.0.1
Summary: Get image object from given url.
Home-page: UNKNOWN
Author: Uros Mrkobrada
Author-email: 
License: GNU General Public License v3
Platform: any
Classifier: Development Status :: 5 - Production/Stable
Classifier: Topic :: Software Development :: User Interfaces
Classifier: Topic :: Utilities
Classifier: Topic :: Desktop Environment
Classifier: Intended Audience :: Developers
Classifier: License :: OSI Approved :: GNU General Public License v3 (GPLv3)
Classifier: Operating System :: OS Independent
Classifier: Programming Language :: Python
Requires-Dist: Pillow
Provides-Extra: dev
Requires-Dist: pytest (>=3.6) ; extra == 'dev'
